{
  "version": "1.0",
  "encoding": "UTF-8",
  "entry": {
    "id": {
      "$t": "tag:blogger.com,1999:blog-post-855847160"
    },
    "title": {
      "type": "text",
      "$t": "Do klopce"
    },
    "author": {
      "name": {
        "$t": "Metod Langus"
      }
    },
    "published": {
      "$t": "2022-12-11T13:38:13.420+0000"
    },
    "updated": {
      "$t": "2022-12-11T13:38:13.420+0000"
    },
    "category": [
      {
        "term": "1. Gorništvo"
      },
      {
        "term": "6. Relive"
      }
    ],
    "content": {
      "$t": "\n<div style=\"display: none;\">\n  <summary>Do klopce</summary>\n</div>\n<span><a name='more'></a></span>\n\n<a href=\"https://img.relive.com/-/w:1600/aHR0cHM6Ly91YS5yZWxpdmUuY2MvMTY0NzMzMTUvMjAyMjEyMTFfMTQxOTM2LmpwZ18xNjcwNzY0Nzc1MDAwLmpwZw==\" style=\"display: block; padding: 1em 0px; text-align: center;\">\n  <img data-skip=\"0;-1\" alt=\"Do klopce\" border=\"0\" src=\"https://img.relive.com/-/w:1000/aHR0cHM6Ly91YS5yZWxpdmUuY2MvMTY0NzMzMTUvMjAyMjEyMTFfMTQxOTM2LmpwZ18xNjcwNzY0Nzc1MDAwLmpwZw==\" width=\"800\" />\n</a>\n\n<hr />\n\n<div class=\"peak-tag\"> \n  <br /><b><span style=\"font-size: 25px;\">Do klopce</span></b><br /><br />\n</div>\n\n<div class=\"separator\" style=\"clear: both;\">\n  <a href=\"https://img.relive.com/-/w:1600/aHR0cHM6Ly91YS5yZWxpdmUuY2MvMTY0NzMzMTUvMjAyMjEyMTFfMTQxOTM2LmpwZ18xNjcwNzY0Nzc1MDAwLmpwZw==\" style=\"display: block; padding: 1em 0px; text-align: center;\">\n    <img data-skip=\"0;-1\" alt=\"Do klopce\" border=\"0\" src=\"https://img.relive.com/-/w:1000/aHR0cHM6Ly91YS5yZWxpdmUuY2MvMTY0NzMzMTUvMjAyMjEyMTFfMTQxOTM2LmpwZ18xNjcwNzY0Nzc1MDAwLmpwZw==\" width=\"600\" />\n  </a>\n</div>\n\n<div class=\"separator\" style=\"clear: both;\">\n  <a href=\"https://img.relive.com/-/w:1600/aHR0cHM6Ly91YS5yZWxpdmUuY2MvMTY0NzMzMTUvMjAyMjEyMTFfMTQyODE1LmpwZ18xNjcwNzY1Mjk0MDAwLmpwZw==\" style=\"display: block; padding: 1em 0px; text-align: center;\">\n    <img data-skip=\"1\" alt=\"Do klopce\" border=\"0\" src=\"https://img.relive.com/-/w:1000/aHR0cHM6Ly91YS5yZWxpdmUuY2MvMTY0NzMzMTUvMjAyMjEyMTFfMTQyODE1LmpwZ18xNjcwNzY1Mjk0MDAwLmpwZw==\" width=\"600\" />\n  </a>\n</div>\n\n<div class=\"separator\" style=\"clear: both;\">\n  <a href=\"https://img.relive.com/-/w:1600/aHR0cHM6Ly91YS5yZWxpdmUuY2MvMTY0NzMzMTUvMjAyMjEyMTFfMTQzNTAwLmpwZ18xNjcwNzY1NzAwMDczLmpwZw==\" style=\"display: block; padding: 1em 0px; text-align: center;\">\n    <img data-skip=\"1\" alt=\"Do klopce\" border=\"0\" src=\"https://img.relive.com/-/w:1000/aHR0cHM6Ly91YS5yZWxpdmUuY2MvMTY0NzMzMTUvMjAyMjEyMTFfMTQzNTAwLmpwZ18xNjcwNzY1NzAwMDczLmpwZw==\" width=\"600\" />\n  </a>\n</div>\n\n<div class=\"separator\" style=\"clear: both;\">\n  <a href=\"https://img.relive.com/-/w:1600/aHR0cHM6Ly91YS5yZWxpdmUuY2MvMTY0NzMzMTUvMjAyMjEyMTFfMTQ0NDEyLmpwZ18xNjcwNzY2MjUwMDAwLmpwZw==\" style=\"display: block; padding: 1em 0px; text-align: center;\">\n    <img data-skip=\"1\" alt=\"Do klopce\" border=\"0\" src=\"https://img.relive.com/-/w:1000/aHR0cHM6Ly91YS5yZWxpdmUuY2MvMTY0NzMzMTUvMjAyMjEyMTFfMTQ0NDEyLmpwZ18xNjcwNzY2MjUwMDAwLmpwZw==\" width=\"600\" />\n  </a>\n</div>\n\n<script>\nvar slideshowTitle0 = 'Make post slideshow';\nvar CoverPhoto0 = 'https://img.relive.com/-/w:1000/aHR0cHM6Ly91YS5yZWxpdmUuY2MvMTY0NzMzMTUvMjAyMjEyMTFfMTQxOTM2LmpwZ18xNjcwNzY0Nzc1MDAwLmpwZw==';\n</script>\n\n<script>\nvar gpxURL0 = \"\";\nvar ReliveURL0 = \"https://www.relive.com/view/vXOnKdAR2B6\";\nvar StravaURL0 = \"\";\n</script>\n"
    },
    "link": [
      {
        "rel": "alternate",
        "type": "text/html",
        "href": "https://metodlangus.github.io/relive/posts/2022/12/do-klopce/index.html"
      },
      {
        "rel": "self",
        "type": "application/json",
        "href": "855847160.json"
      }
    ],
    "media$thumbnail": {
      "xmlns$media": "http://search.yahoo.com/mrss/",
      "url": "https://img.relive.com/-/w:600/aHR0cHM6Ly91YS5yZWxpdmUuY2MvMTY0NzMzMTUvMjAyMjEyMTFfMTQxOTM2LmpwZ18xNjcwNzY0Nzc1MDAwLmpwZw==",
      "height": "auto",
      "width": "600"
    }
  }
}